{
    "visualization_prompt": "Create a Highcharts chartOptions object to render a mirrored horizontal column chart (bar chart) with stacking. The chart should display the population distribution by age groups for Andorra in 2023. The chart should have two mirrored x-axes, one for male and one for female populations. The title of the chart should be 'Population pyramid for Andorra, 2023', and the subtitle should include a source link. The y-axis should display the percentage population, and the tooltip should show the series name, age category, and population percentage. The chart should use custom colors for the series and have specific styling for labels, axes, and titles.",
    "visualization_code": {
        "chart": {
            "type": "bar"
        },
        "title": {
            "text": "Population pyramid for Andorra, 2023",
            "align": "left"
        },
        "subtitle": {
            "text": "Source: <a href='https://countryeconomy.com/demography/population-structure/andorra' target='_blank'>countryeconomy.com</a>",
            "align": "left"
        },
        "accessibility": {
            "point": {
                "valueDescriptionFormat": "{index}. Age {xDescription}, {value}%."
            }
        },
        "xAxis": [
            {
                "categories": [
                    "0-4",
                    "5-9",
                    "10-14",
                    "15-19",
                    "20-24",
                    "25-29",
                    "30-34",
                    "35-40",
                    "40-45",
                    "45-49",
                    "50-54",
                    "55-59",
                    "60-64",
                    "65-69",
                    "70-74",
                    "75-79",
                    "80-84",
                    "80+"
                ],
                "reversed": false,
                "labels": {
                    "step": 1
                },
                "accessibility": {
                    "description": "Age (male)"
                }
            },
            {
                "opposite": true,
                "reversed": false,
                "categories": [
                    "0-4",
                    "5-9",
                    "10-14",
                    "15-19",
                    "20-24",
                    "25-29",
                    "30-34",
                    "35-40",
                    "40-45",
                    "45-49",
                    "50-54",
                    "55-59",
                    "60-64",
                    "65-69",
                    "70-74",
                    "75-79",
                    "80-84",
                    "80+"
                ],
                "linkedTo": 0,
                "labels": {
                    "step": 1
                },
                "accessibility": {
                    "description": "Age (female)"
                }
            }
        ],
        "yAxis": {
            "title": {
                "text": null
            },
            "labels": {
                "format": "{abs value}%"
            },
            "accessibility": {
                "description": "Percentage population",
                "rangeDescription": "Range: 0 to 5%"
            }
        },
        "plotOptions": {
            "series": {
                "stacking": "normal",
                "borderRadius": "50%"
            }
        },
        "tooltip": {
            "format": "<b>{series.name}, age {point.category}</b><br/>Population: {(abs point.y):.2f}%"
        },
        "series": [
            {
                "name": "Male",
                "data": [
                    -1.38,
                    -2.09,
                    -2.45,
                    -2.71,
                    -2.97,
                    -3.69,
                    -4.04,
                    -3.81,
                    -4.19,
                    -4.61,
                    -4.56,
                    -4.21,
                    -3.53,
                    -2.55,
                    -1.82,
                    -1.46,
                    -0.78,
                    -0.71
                ]
            },
            {
                "name": "Female",
                "data": [
                    1.35,
                    1.98,
                    2.43,
                    2.39,
                    2.71,
                    3.02,
                    3.5,
                    3.52,
                    4.03,
                    4.4,
                    4.17,
                    3.88,
                    3.29,
                    2.42,
                    1.8,
                    1.39,
                    0.99,
                    1.15
                ]
            }
        ],
        "colors": [
            "#7cb5ec",
            "#434348"
        ]
    },
    "visualization_explanation": "The provided Highcharts chartOptions object is configured to render a mirrored horizontal column chart (bar chart) with stacking. This chart is designed to display the population distribution by age groups for Andorra in 2023. The chart features two mirrored x-axes, one for male and one for female populations, with age categories ranging from '0-4' to '80+'. The y-axis represents the percentage population, and the tooltip provides detailed information about the series name, age category, and population percentage. The chart title is 'Population pyramid for Andorra, 2023', and the subtitle includes a source link for reference. The chart uses custom colors for the series and has specific styling for labels, axes, and titles to enhance readability and accessibility."
}