{
    "visualization_prompt": "Generate a combination chart showing monthly temperature and rainfall trends using dual series with line and column types",
    "visualization_code": {
        "chart": {
            "type": "line",
            "backgroundColor": "#ffffff",
            "margin": [
                40,
                40,
                80,
                80
            ]
        },
        "title": {
            "text": "Monthly Temperature and Rainfall Data (2023)",
            "align": "left",
            "style": {
                "color": "#2c3e50",
                "fontSize": "18px",
                "fontWeight": "bold"
            }
        },
        "xAxis": {
            "categories": [
                "Jan",
                "Feb",
                "Mar",
                "Apr",
                "May",
                "Jun",
                "Jul",
                "Aug",
                "Sep",
                "Oct",
                "Nov",
                "Dec"
            ],
            "labels": {
                "style": {
                    "color": "#7f8c8d",
                    "fontSize": "12px"
                }
            },
            "title": {
                "text": "Month",
                "style": {
                    "color": "#34495e",
                    "fontSize": "14px",
                    "fontWeight": "bold"
                }
            }
        },
        "yAxis": {
            "title": {
                "text": "Values",
                "style": {
                    "color": "#34495e",
                    "fontSize": "14px",
                    "fontWeight": "bold"
                }
            },
            "labels": {
                "style": {
                    "color": "#7f8c8d",
                    "fontSize": "12px"
                }
            }
        },
        "series": [
            {
                "name": "Temperature (\u00b0F)",
                "type": "line",
                "data": [
                    29.9,
                    71.5,
                    106.4,
                    129.2,
                    144.0,
                    176.0,
                    135.6,
                    148.5,
                    216.4,
                    194.1,
                    95.6,
                    54.4
                ],
                "color": "#3498db",
                "marker": {
                    "symbol": "circle",
                    "radius": 4
                }
            },
            {
                "name": "Rainfall (mm)",
                "type": "column",
                "data": [
                    194.1,
                    95.6,
                    54.4,
                    29.9,
                    71.5,
                    106.4,
                    129.2,
                    144.0,
                    176.0,
                    135.6,
                    148.5,
                    216.4
                ],
                "color": "#2ecc71"
            }
        ],
        "legend": {
            "align": "center",
            "verticalAlign": "bottom",
            "itemStyle": {
                "color": "#34495e",
                "fontSize": "12px"
            }
        },
        "tooltip": {
            "shared": true,
            "valueDecimals": 1,
            "valueSuffix": " units"
        }
    },
    "visualization_explanation": "The dataset contains two time-aligned series with 12 monthly observations each. Temperature uses interval data (Fahrenheit scale) while rainfall employs ratio measurements (millimeters). Though synthetic, the data maintains domain consistency through plausible value ranges (temperature: \u03bc=121.3, \u03c3=55.9; rainfall: \u03bc=125.5, \u03c3=55.1) and logical seasonal progression with summer peaks. The combination chart maximizes data-ink ratio by using a shared temporal axis while differentiating variables through Tufte's fundamental contrast of line vs column encoding. Cairo's perceptual principles are applied through pre-attentive color coding (blue=thermodynamic variable, green=precipitation) and proportional width in column elements. Dual encoding allows direct comparison of two distinct climate dimensions without dual-axis distortion."
}