{
    "visualization_prompt": "Generate a polar chart showing cyclical data patterns using multiple series types (column/line/area) with angular coordinates",
    "visualization_code": {
        "chart": {
            "polar": true,
            "type": "line"
        },
        "title": {
            "text": "Highcharts Polar Chart",
            "style": {
                "fontSize": "18px",
                "color": "#333"
            }
        },
        "pane": {
            "startAngle": 0,
            "endAngle": 360
        },
        "xAxis": {
            "tickInterval": 45,
            "min": 0,
            "max": 360,
            "labels": {
                "formatter": "function() { return this.value + '\u00b0'; }",
                "style": {
                    "color": "#666",
                    "fontSize": "12px"
                }
            }
        },
        "yAxis": {
            "min": 0,
            "labels": {
                "style": {
                    "color": "#666",
                    "fontSize": "12px"
                }
            }
        },
        "plotOptions": {
            "series": {
                "pointStart": 0,
                "pointInterval": 45
            },
            "column": {
                "pointPadding": 0,
                "groupPadding": 0
            }
        },
        "series": [
            {
                "type": "column",
                "name": "Radial Distribution",
                "data": [
                    8,
                    7,
                    6,
                    5,
                    4,
                    3,
                    2,
                    1
                ],
                "color": "#7CB5EC",
                "pointPlacement": "between"
            },
            {
                "type": "line",
                "name": "Angular Progression",
                "data": [
                    1,
                    2,
                    3,
                    4,
                    5,
                    6,
                    7,
                    8
                ],
                "color": "#434348",
                "marker": {
                    "enabled": true
                }
            },
            {
                "type": "area",
                "name": "Cyclical Pattern",
                "data": [
                    1,
                    8,
                    2,
                    7,
                    3,
                    6,
                    4,
                    5
                ],
                "color": "#90ED7D",
                "fillOpacity": 0.4
            }
        ]
    },
    "visualization_explanation": "The dataset contains three 8-dimensional series representing angular measurements at 45\u00b0 increments. Categorical variables are encoded as angular positions (0-360\u00b0), while quantitative values range 0-8 on the radial axis. Synthetic data demonstrates inverse (column), linear (line), and alternating (area) patterns for comparison. Polar coordinates effectively reveal directional relationships while maintaining Tufte's data-ink ratio through minimal gridlines. Cairo's perceptual principles are applied through: 1) Hue differentiation for series, 2) Area opacity for layer separation, 3) Angular labels with degree symbols. Column series uses 'between' placement to avoid tick overlap, while line markers enhance position clarity. The symmetric layout supports direct comparison of multiple distribution patterns in circular space."
}