{
    "visualization_prompt": "Create a Highcharts timeline chart with the title 'Timeline of Space Exploration'. The chart should have invisible x and y axes. The data series should include events such as 'First dogs in space', 'Sputnik 1', 'First human spaceflight', and 'First human on the Moon'. Each event should have a label and a description. The chart should have a subtitle with a link to the source of the information. The chart should be styled with specific colors for the labels and titles, and should have a custom background color.",
    "visualization_code": {
        "chart": {
            "type": "timeline",
            "backgroundColor": "#f0f8ff"
        },
        "xAxis": {
            "visible": false
        },
        "yAxis": {
            "visible": false
        },
        "title": {
            "text": "Timeline of Space Exploration",
            "style": {
                "color": "#000080",
                "fontSize": "20px"
            }
        },
        "subtitle": {
            "text": "Info source: <a href=\"https://en.wikipedia.org/wiki/Timeline_of_space_exploration\">www.wikipedia.org</a>",
            "style": {
                "color": "#000080",
                "fontSize": "14px"
            }
        },
        "series": [
            {
                "data": [
                    {
                        "name": "First dogs",
                        "label": "1951: First dogs in space",
                        "description": "22 July 1951 First dogs in space (Dezik and Tsygan)",
                        "color": "#8a2be2"
                    },
                    {
                        "name": "Sputnik 1",
                        "label": "1957: First artificial satellite",
                        "description": "4 October 1957 First artificial satellite. First signals from space.",
                        "color": "#ff69b4"
                    },
                    {
                        "name": "First human spaceflight",
                        "label": "1961: First human spaceflight (Yuri Gagarin)",
                        "description": "First human spaceflight (Yuri Gagarin), and the first human-crewed orbital flight",
                        "color": "#ffa500"
                    },
                    {
                        "name": "First human on the Moon",
                        "label": "1969: First human on the Moon",
                        "description": "First human on the Moon, and first space launch from a celestial body other than the Earth. First sample return from the Moon",
                        "color": "#008000"
                    }
                ]
            }
        ]
    },
    "visualization_explanation": "The provided Highcharts configuration object is designed to render a timeline chart with specific styling and data series. The chart type is set to 'timeline', and the background color is customized to a light blue shade (#f0f8ff). The x and y axes are set to be invisible, focusing the viewer's attention on the timeline events. The title and subtitle are styled with navy blue text and specific font sizes to enhance readability. The data series includes four key events in the timeline of space exploration, each with a unique color to distinguish them. The colors used are a mix of classic and vibrant shades to make the events stand out. The subtitle includes a hyperlink to the source of the information, ensuring credibility and providing a reference for further reading."
}