{
    "visualization_prompt": "Create a Highcharts chartOptions object to render a spline chart with the title 'Monthly Average Temperature'. The chart should have styled axes and labels with specific colors and font sizes. The data series should represent the monthly average temperature for a year. Custom colors should be used for the series, and additional configurations should include chart margins, background, and legend settings.",
    "visualization_code": {
        "chart": {
            "type": "spline",
            "styledMode": true,
            "margin": [
                50,
                50,
                100,
                80
            ],
            "backgroundColor": "#f9f9f9"
        },
        "title": {
            "text": "Monthly Average Temperature",
            "style": {
                "color": "#333333",
                "fontSize": "20px"
            }
        },
        "xAxis": {
            "categories": [
                "Jan",
                "Feb",
                "Mar",
                "Apr",
                "May",
                "Jun",
                "Jul",
                "Aug",
                "Sep",
                "Oct",
                "Nov",
                "Dec"
            ],
            "labels": {
                "style": {
                    "color": "#666666",
                    "fontSize": "14px"
                }
            },
            "title": {
                "text": "Months",
                "style": {
                    "color": "#444444",
                    "fontSize": "16px"
                }
            }
        },
        "yAxis": {
            "title": {
                "text": "Temperature (\u00b0C)",
                "style": {
                    "color": "#444444",
                    "fontSize": "16px"
                }
            },
            "labels": {
                "style": {
                    "color": "#666666",
                    "fontSize": "14px"
                }
            }
        },
        "series": [
            {
                "name": "Temperature",
                "data": [
                    29.9,
                    71.5,
                    106.4,
                    129.2,
                    144.0,
                    176.0,
                    135.6,
                    148.5,
                    216.4,
                    194.1,
                    95.6,
                    54.4
                ],
                "color": "#FF6347"
            }
        ],
        "legend": {
            "enabled": true,
            "itemStyle": {
                "color": "#555555",
                "fontSize": "14px"
            }
        }
    },
    "visualization_explanation": "The provided Highcharts chartOptions object is configured to render a spline chart with a title 'Monthly Average Temperature'. The chart type is set to 'spline', and it includes custom styling for the title, axes, and labels. The title and axis titles have specific font sizes and colors, enhancing readability. The data series represents the monthly average temperature for a year, with custom colors applied to the series. Additional configurations include setting the chart margins, background color, and enabling the legend with custom styling. This setup ensures a visually appealing and informative chart."
}