{
    "visualization_prompt": "Generate a line chart showing monthly trends for two synthetic datasets using differentiated z-index layering and width variation",
    "visualization_code": {
        "chartOptions": {
            "chart": {
                "type": "line",
                "marginRight": 50,
                "marginLeft": 50,
                "backgroundColor": "#FFFFFF"
            },
            "title": {
                "text": "Monthly Performance Comparison 2023",
                "style": {
                    "fontSize": "16px",
                    "color": "#2C3E50"
                }
            },
            "xAxis": {
                "categories": [
                    "Jan",
                    "Feb",
                    "Mar",
                    "Apr",
                    "May",
                    "Jun",
                    "Jul",
                    "Aug",
                    "Sep",
                    "Oct",
                    "Nov",
                    "Dec"
                ],
                "labels": {
                    "style": {
                        "color": "#333333",
                        "fontSize": "12px"
                    }
                }
            },
            "yAxis": {
                "title": {
                    "text": "Metric Value",
                    "style": {
                        "color": "#333333",
                        "fontSize": "12px"
                    }
                },
                "labels": {
                    "style": {
                        "color": "#333333",
                        "fontSize": "12px"
                    }
                }
            },
            "series": [
                {
                    "name": "Series A (Growth Pattern)",
                    "data": [
                        32,
                        47,
                        63,
                        78,
                        88,
                        104,
                        97,
                        115,
                        132,
                        147,
                        165,
                        184
                    ],
                    "color": "#2E86C1",
                    "lineWidth": 5,
                    "zIndex": 2
                },
                {
                    "name": "Series B (Seasonal Pattern)",
                    "data": [
                        124,
                        135,
                        142,
                        153,
                        162,
                        173,
                        168,
                        157,
                        146,
                        138,
                        127,
                        118
                    ],
                    "color": "#F4D03F",
                    "lineWidth": 3,
                    "zIndex": 1
                }
            ],
            "legend": {
                "layout": "horizontal",
                "align": "center",
                "verticalAlign": "bottom",
                "itemStyle": {
                    "color": "#333333",
                    "fontSize": "12px"
                }
            }
        }
    },
    "visualization_explanation": "The dataset contains two 12-dimensional time series with monthly temporal resolution. Series A exhibits a positive linear trend (\u03bc=116.8, \u03c3=49.3) with minor mid-year fluctuations, while Series B demonstrates seasonal characteristics (\u03bc=144.3, \u03c3=17.1) peaking in summer months. Synthetic data was generated using trend-line equations with added normally distributed noise (\u03c3=5% of mean value) to simulate real-world variance. The line chart format was selected to emphasize temporal progression, with Tufte's data-ink ratio optimized through minimal gridlines and direct labeling. Cairo's perceptual principles are applied through width differentiation (5px vs 3px) and z-index layering to ensure visual dominance of Series A. Color choices (#2E86C1 vs #F4D03F) maintain 3:1 contrast ratio for accessibility while avoiding red-green chromatic conflict."
}