{
    "visualization_prompt": "Create a Highcharts chartOptions object to render a spline chart with the title 'Monthly Average Temperature'. The chart should have styled axes and labels with specific colors and font sizes. The data series should represent the monthly average temperature for a year, with a dotted line indicating a prognosis after August. The chart should have custom colors and additional configurations such as chart margins, background, and legend settings.",
    "visualization_code": {
        "chart": {
            "type": "spline",
            "backgroundColor": "#f9f9f9",
            "marginTop": 50,
            "marginBottom": 100,
            "marginLeft": 70,
            "marginRight": 70
        },
        "title": {
            "text": "Monthly Average Temperature",
            "style": {
                "color": "#333",
                "fontSize": "20px",
                "fontWeight": "bold"
            }
        },
        "subtitle": {
            "text": "Dotted line typically signifies prognosis",
            "style": {
                "color": "#666",
                "fontSize": "14px"
            }
        },
        "xAxis": {
            "categories": [
                "Jan",
                "Feb",
                "Mar",
                "Apr",
                "May",
                "Jun",
                "Jul",
                "Aug",
                "Sep",
                "Oct",
                "Nov",
                "Dec"
            ],
            "labels": {
                "style": {
                    "color": "#555",
                    "fontSize": "12px"
                }
            },
            "title": {
                "text": "Months",
                "style": {
                    "color": "#444",
                    "fontSize": "14px"
                }
            }
        },
        "yAxis": {
            "title": {
                "text": "Temperature (\u00b0C)",
                "style": {
                    "color": "#444",
                    "fontSize": "14px"
                }
            },
            "labels": {
                "style": {
                    "color": "#555",
                    "fontSize": "12px"
                }
            }
        },
        "series": [
            {
                "name": "Temperature",
                "data": [
                    29.9,
                    71.5,
                    106.4,
                    129.2,
                    144.0,
                    176.0,
                    135.6,
                    148.5,
                    216.4,
                    194.1,
                    95.6,
                    54.4
                ],
                "zoneAxis": "x",
                "zones": [
                    {
                        "value": 8
                    },
                    {
                        "dashStyle": "dot"
                    }
                ],
                "color": "#0073e6"
            }
        ],
        "legend": {
            "enabled": true,
            "itemStyle": {
                "color": "#333",
                "fontSize": "12px"
            }
        }
    },
    "visualization_explanation": "The provided Highcharts chartOptions object configures a spline chart with a title 'Monthly Average Temperature' and a subtitle explaining the dotted line as a prognosis. The x-axis represents the months of the year with styled labels and a title. The y-axis represents the temperature in degrees Celsius, also with styled labels and a title. The data series includes the monthly average temperatures for a year, with a custom color and a zone configuration to apply a dotted line style after August. The chart has custom margins and a light background color. The legend is enabled with styled text to provide additional context for the chart."
}