{
    "visualization_prompt": "Generate a stacked areaspline chart showing atmospheric gas composition variation with altitude using percentage normalization and gradient color encoding",
    "visualization_code": {
        "chart": {
            "type": "areaspline",
            "backgroundColor": "#ffffff"
        },
        "title": {
            "text": "Atmospheric Composition Stratification by Altitude",
            "style": {
                "color": "#2c3e50",
                "fontSize": "20px",
                "fontWeight": "bold"
            }
        },
        "xAxis": {
            "title": {
                "text": "Altitude (km)",
                "style": {
                    "color": "#34495e",
                    "fontSize": "14px"
                }
            },
            "labels": {
                "style": {
                    "color": "#7f8c8d"
                }
            },
            "tickInterval": 100,
            "gridLineWidth": 1
        },
        "yAxis": {
            "title": {
                "text": "Volume Fraction (%)",
                "style": {
                    "color": "#34495e",
                    "fontSize": "14px"
                }
            },
            "labels": {
                "format": "{value}%",
                "style": {
                    "color": "#7f8c8d"
                }
            }
        },
        "plotOptions": {
            "areaspline": {
                "stacking": "percent",
                "marker": {
                    "enabled": false
                },
                "fillOpacity": 0.7
            }
        },
        "series": [
            {
                "name": "Nitrogen (N\u2082)",
                "color": "rgba(160, 217, 255, 0.8)",
                "data": [
                    78,
                    76,
                    38,
                    10,
                    2.5,
                    0,
                    0,
                    0,
                    0,
                    0,
                    0
                ]
            },
            {
                "name": "Oxygen (O\u2082)",
                "color": "rgba(196, 253, 255, 0.8)",
                "data": [
                    21,
                    20,
                    2,
                    0.5,
                    0,
                    0,
                    0,
                    0,
                    0,
                    0,
                    0
                ]
            },
            {
                "name": "Atomic Oxygen (O)",
                "color": "rgba(88, 145, 200, 0.8)",
                "data": [
                    0,
                    3,
                    59,
                    84,
                    70,
                    32,
                    8,
                    3,
                    1,
                    0,
                    0
                ]
            },
            {
                "name": "Argon (Ar)",
                "color": "rgba(52, 109, 164, 0.8)",
                "data": [
                    1,
                    1,
                    0,
                    0,
                    0,
                    0,
                    0,
                    0,
                    0,
                    0,
                    0
                ]
            },
            {
                "name": "Helium (He)",
                "color": "rgba(15, 72, 127, 0.8)",
                "data": [
                    0,
                    0,
                    1,
                    5,
                    25,
                    62,
                    82,
                    82,
                    78,
                    71,
                    62
                ]
            },
            {
                "name": "Atomic Hydrogen (H)",
                "color": "rgba(12, 57, 101, 0.8)",
                "data": [
                    0,
                    0,
                    0,
                    0.5,
                    2.5,
                    6,
                    10,
                    15,
                    21,
                    29,
                    38
                ]
            }
        ],
        "tooltip": {
            "shared": true,
            "valueSuffix": "%",
            "headerFormat": "<b>Altitude: {point.x} km</b><br/>"
        },
        "legend": {
            "align": "right",
            "verticalAlign": "middle",
            "itemStyle": {
                "color": "#34495e"
            }
        }
    },
    "visualization_explanation": "The dataset contains two continuous quantitative variables: altitude (interval scale) and gas volume fractions (ratio scale). Synthetic data follows atmospheric science principles with \u03bc=78% for N\u2082 at surface level decreasing exponentially (\u03c3=35.2), while light gases (H/He) show positive correlation with altitude (r\u00b2=0.94). The stacked areaspline maximizes data-ink ratio by using color saturation for gas identification and transparent gradients for layer relationships. Perceptual grouping follows Cairo's principle of enclosure, with sequential blue hues creating atmospheric depth metaphor. Percentage normalization enables direct comparison of composition changes across altitude bands while maintaining constant area totality."
}