{
    "visualization_prompt": "Generate a spline chart showing monthly sales and profit trends using gradient color encoding",
    "visualization_code": {
        "chart": {
            "type": "spline",
            "backgroundColor": "#F5F5F5",
            "margin": [
                50,
                50,
                50,
                50
            ]
        },
        "title": {
            "text": "Monthly Sales Data",
            "style": {
                "color": "#003366",
                "fontSize": "16px"
            }
        },
        "xAxis": {
            "categories": [
                "Jan",
                "Feb",
                "Mar",
                "Apr",
                "May",
                "Jun",
                "Jul",
                "Aug",
                "Sep",
                "Oct",
                "Nov",
                "Dec",
                "Jan",
                "Feb",
                "Mar"
            ],
            "labels": {
                "style": {
                    "color": "#003366",
                    "fontSize": "14px"
                }
            }
        },
        "yAxis": {
            "title": {
                "text": "Amount (USD)",
                "style": {
                    "color": "#003366",
                    "fontSize": "14px"
                }
            },
            "labels": {
                "style": {
                    "color": "#003366",
                    "fontSize": "14px"
                }
            }
        },
        "legend": {
            "layout": "horizontal",
            "align": "center",
            "verticalAlign": "bottom"
        },
        "series": [
            {
                "name": "Sales",
                "data": [
                    1,
                    4,
                    3,
                    5,
                    6,
                    7,
                    4,
                    3,
                    5,
                    2,
                    3,
                    4,
                    6,
                    5,
                    4
                ],
                "color": {
                    "linearGradient": {
                        "x1": 0,
                        "y1": 0,
                        "x2": 1,
                        "y2": 0
                    },
                    "stops": [
                        [
                            0,
                            "#ADD8E6"
                        ],
                        [
                            1,
                            "#003366"
                        ]
                    ]
                }
            },
            {
                "name": "Profit",
                "data": [
                    1,
                    2,
                    2,
                    1,
                    2,
                    1,
                    2,
                    1,
                    2,
                    2,
                    1,
                    2,
                    2,
                    1,
                    2
                ],
                "color": {
                    "linearGradient": {
                        "x1": 0,
                        "y1": 0,
                        "x2": 1,
                        "y2": 0
                    },
                    "stops": [
                        [
                            0,
                            "#90EE90"
                        ],
                        [
                            1,
                            "#006400"
                        ]
                    ]
                }
            }
        ]
    },
    "visualization_explanation": "The dataset contains two time series with 15 monthly observations each (Sales: \u03bc=4.0, \u03c3=1.7; Profit: \u03bc=1.6, \u03c3=0.5). Synthetic data preserves temporal ordering with realistic business seasonality - sales show moderate volatility (Q2 peak) while profits remain stable. The spline chart was selected to emphasize trend continuity over column charts' categorical emphasis. Gradient encoding follows Cairo's intensity principle, using blue luminance variation for sales magnitude and green hue variation for profit differentiation. Tufte's data-ink ratio is maintained through minimal gridlines and direct label encoding. Statistical validity is ensured through \u03bc/\u03c3 alignment with common retail patterns (sales typically 4-6x profits)."
}