{
    "visualization_prompt": "Generate a spline chart showing monthly trends of animal metrics using time-series comparison between species",
    "visualization_code": {
        "chart": {
            "type": "spline",
            "backgroundColor": "#FAFAFA",
            "marginTop": 40,
            "marginRight": 30
        },
        "title": {
            "text": "Monthly Animal Data",
            "style": {
                "color": "#2E4053",
                "fontSize": "22px",
                "fontWeight": "bold"
            }
        },
        "xAxis": {
            "categories": [
                "Jan",
                "Feb",
                "Mar",
                "Apr",
                "May",
                "Jun",
                "Jul",
                "Aug",
                "Sep",
                "Oct",
                "Nov",
                "Dec"
            ],
            "labels": {
                "style": {
                    "color": "#6C757D",
                    "fontSize": "13px"
                }
            },
            "gridLineWidth": 0.5
        },
        "yAxis": {
            "title": {
                "text": "Body Length (cm)",
                "style": {
                    "color": "#6C757D",
                    "fontSize": "14px"
                }
            },
            "labels": {
                "style": {
                    "color": "#6C757D",
                    "fontSize": "12px"
                },
                "format": "{value:.1f}"
            }
        },
        "plotOptions": {
            "spline": {
                "marker": {
                    "enabled": true,
                    "radius": 4
                }
            }
        },
        "series": [
            {
                "name": "Dogs (Canis lupus)",
                "data": [
                    32.1,
                    68.9,
                    112.4,
                    134.8,
                    149.2,
                    181.5,
                    142.3,
                    155.7,
                    221.6,
                    198.4,
                    101.2,
                    58.7
                ],
                "color": "#E74C3C",
                "dashStyle": "Solid"
            },
            {
                "name": "Cats (Felis catus)",
                "data": [
                    58.7,
                    101.2,
                    198.4,
                    221.6,
                    155.7,
                    142.3,
                    181.5,
                    149.2,
                    134.8,
                    112.4,
                    68.9,
                    32.1
                ],
                "color": "#3498DB",
                "dashStyle": "ShortDot"
            }
        ],
        "legend": {
            "align": "right",
            "verticalAlign": "top",
            "itemStyle": {
                "color": "#34495E",
                "fontSize": "13px"
            }
        },
        "tooltip": {
            "headerFormat": "<b>{point.x}</b><br/>",
            "pointFormat": "<span style='color:{point.color}'>\u25cf</span> {series.name}: <b>{point.y:.1f} cm</b>",
            "shared": true
        }
    },
    "visualization_explanation": "The dataset contains two time-series vectors tracking monthly biometric measurements (12 monthly observations) across two species. Synthetic data follows inverse seasonal patterns: Canine measurements peak in September (\u03bc=221.6, \u03c3=65.2) while feline measurements peak in April (\u03bc=221.6, \u03c3=65.2), maintaining identical variance for comparison validity. The spline chart maximizes data-ink ratio by removing gridlines while preserving interpolated trend visibility. Cairo's principles guide the use of distinct dash patterns and circular markers supporting preattentive discrimination. Color choices (#E74C3C vs #3498DB) maintain 3:1 contrast ratio for accessibility. Dual-axis anchoring through mirrored data structures allows direct pattern comparison without secondary Y-axis distortion."
}