{
    "visualization_prompt": "Create a Highcharts chartOptions object to render a column chart titled 'Color Distribution'. The chart should have axes and labels styled with specific colors and font sizes. The data series should include the names 'Green', 'Yellow', 'Blue', and 'Red' with corresponding data values. Custom colors should be applied to each series. Additional configurations should include chart margins, background, and legend settings.",
    "visualization_code": {
        "chart": {
            "type": "column",
            "backgroundColor": "#f9f9f9",
            "marginTop": 50,
            "marginBottom": 100
        },
        "title": {
            "text": "Color Distribution",
            "style": {
                "color": "#333",
                "fontSize": "20px"
            }
        },
        "xAxis": {
            "categories": [
                "Green",
                "Yellow",
                "Blue",
                "Red"
            ],
            "labels": {
                "style": {
                    "color": "#555",
                    "fontSize": "14px"
                }
            },
            "title": {
                "text": "Colors",
                "style": {
                    "color": "#777",
                    "fontSize": "16px"
                }
            }
        },
        "yAxis": {
            "title": {
                "text": "Value",
                "style": {
                    "color": "#777",
                    "fontSize": "16px"
                }
            },
            "labels": {
                "style": {
                    "color": "#555",
                    "fontSize": "14px"
                }
            }
        },
        "series": [
            {
                "name": "Green",
                "data": [
                    10
                ],
                "color": "green"
            },
            {
                "name": "Yellow",
                "data": [
                    15
                ],
                "color": "yellow"
            },
            {
                "name": "Blue",
                "data": [
                    20
                ],
                "color": "blue"
            },
            {
                "name": "Red",
                "data": [
                    25
                ],
                "color": "red"
            }
        ],
        "legend": {
            "enabled": true,
            "itemStyle": {
                "color": "#444",
                "fontSize": "14px"
            }
        }
    },
    "visualization_explanation": "The provided Highcharts chartOptions object configures a column chart titled 'Color Distribution'. The chart type is set to 'column', and it includes specific styling for the title, axes, and labels. The x-axis categories represent the colors 'Green', 'Yellow', 'Blue', and 'Red', while the y-axis represents the corresponding values. Each series is assigned a custom color matching its name. The chart's background is set to a light gray, and margins are adjusted for better spacing. The legend is enabled and styled with a dark gray color and a font size of 14px."
}