{
    "visualization_prompt": "Create a Highcharts chartOptions object to render a gauge chart with the following specifications: Chart type: gauge, Chart title: 'Speedometer', Axes and labels styling: Define colors, font sizes, or styles for labels, axes, and titles, Data series: Provide the data for each series, including the name of each series and its data, formatted appropriately for Highcharts, Custom colors: Specific list of colors, if desired, Additional configurations: Other settings, such as chart margins, background, legend, etc.",
    "visualization_code": {
        "chart": {
            "type": "gauge",
            "plotBackgroundColor": null,
            "plotBackgroundImage": null,
            "plotBorderWidth": 0,
            "plotShadow": false,
            "height": "80%"
        },
        "title": {
            "text": "Speedometer"
        },
        "pane": {
            "startAngle": -90,
            "endAngle": 89.9,
            "background": null,
            "center": [
                "50%",
                "75%"
            ],
            "size": "110%"
        },
        "yAxis": {
            "min": 0,
            "max": 200,
            "tickPixelInterval": 72,
            "tickPosition": "inside",
            "tickColor": "#FFFFFF",
            "tickLength": 20,
            "tickWidth": 2,
            "minorTickInterval": null,
            "labels": {
                "distance": 20,
                "style": {
                    "fontSize": "14px"
                }
            },
            "lineWidth": 0,
            "plotBands": [
                {
                    "from": 0,
                    "to": 130,
                    "color": "#55BF3B",
                    "thickness": 20,
                    "borderRadius": "50%"
                },
                {
                    "from": 150,
                    "to": 200,
                    "color": "#DF5353",
                    "thickness": 20,
                    "borderRadius": "50%"
                },
                {
                    "from": 120,
                    "to": 160,
                    "color": "#DDDF0D",
                    "thickness": 20
                }
            ]
        },
        "series": [
            {
                "name": "Speed",
                "data": [
                    80
                ],
                "tooltip": {
                    "valueSuffix": " km/h"
                },
                "dataLabels": {
                    "format": "{y} km/h",
                    "borderWidth": 0,
                    "color": "#333333",
                    "style": {
                        "fontSize": "16px"
                    }
                },
                "dial": {
                    "radius": "80%",
                    "backgroundColor": "gray",
                    "baseWidth": 12,
                    "baseLength": "0%",
                    "rearLength": "0%"
                },
                "pivot": {
                    "backgroundColor": "gray",
                    "radius": 6
                }
            }
        ]
    },
    "visualization_explanation": "The provided Highcharts chartOptions object is configured to render a gauge chart with a title 'Speedometer'. The chart type is set to 'gauge', and it includes specific styling for the axes and labels, such as font sizes and colors. The data series consists of a single series named 'Speed' with an initial value of 80, formatted to display ' km/h' as a suffix in tooltips. The gauge includes custom plot bands with specific colors and thicknesses to indicate different speed ranges. Additional configurations include settings for the chart's background, margins, and the gauge's dial and pivot styling."
}